{
  "agent": "shopping",
  "status": "complete",
  "data_source": "curated_knowledge",
  "notes": "MCP servers (RedNote, Gaode Maps) unavailable during research. Recommendations based on well-established shopping destinations. All locations should be verified for operating hours before visit. Budget allocation is conservative (¥1500 total) given minimal shopping requirements.",
  "data": {
    "days": [
      {
        "day": 5,
        "date": "2026-02-19",
        "location": "Shanghai",
        "shopping": [
          {
            "name": "钟书阁 (Zhongshuge Bookstore)",
            "category": "indie_bookstore",
            "location": "芮欧百货, 南京西路1601号",
            "estimated_budget": 200,
            "notes": "Famous 'most beautiful bookstore in China'. Has English section. Near hotel location. Open 10:00-22:00."
          },
          {
            "name": "泡泡玛特旗舰店 (POP MART Flagship)",
            "category": "designer_toys",
            "location": "TX淮海年轻力中心, 淮海中路523号",
            "estimated_budget": 300,
            "notes": "Large POP MART flagship with exclusive releases. Perfect for girlfriend's interests. Open 10:00-22:00."
          }
        ],
        "daily_shopping_budget": 500
      },
      {
        "day": 7,
        "date": "2026-02-21",
        "location": "Shanghai",
        "shopping": [
          {
            "name": "新天地时尚购物区",
            "category": "fashion_district",
            "location": "黄浦区太仓路181弄",
            "estimated_budget": 500,
            "notes": "Upscale fashion boutiques, international brands, trendy stores. Great for quality fashion items. Mix of Chinese and Western brands."
          },
          {
            "name": "田子坊",
            "category": "boutique_shopping",
            "location": "泰康路210弄",
            "estimated_budget": 200,
            "notes": "Artistic shopping area with unique boutiques, indie designers, cute accessories. Less touristy than expected."
          },
          {
            "name": "言几又书店",
            "category": "lifestyle_bookstore",
            "location": "大悦城北座, 西藏北路166号",
            "estimated_budget": 100,
            "notes": "Modern lifestyle bookstore with English section, design items, cute stationery. Open 10:00-22:00."
          }
        ],
        "daily_shopping_budget": 800
      },
      {
        "day": 14,
        "date": "2026-02-28",
        "location": "Beijing",
        "shopping": [
          {
            "name": "PageOne书店 (三里屯店)",
            "category": "english_bookstore",
            "location": "三里屯太古里南区, 三里屯路19号",
            "estimated_budget": 150,
            "notes": "Best English bookstore in Beijing. Large foreign language section. Modern design. Open 10:00-22:00."
          },
          {
            "name": "泡泡玛特 (POP MART 三里屯旗舰店)",
            "category": "designer_toys",
            "location": "三里屯太古里南区",
            "estimated_budget": 250,
            "notes": "Large flagship store with exclusive toys. Same shopping area as PageOne for convenience."
          },
          {
            "name": "The Bookworm",
            "category": "english_bookstore_cafe",
            "location": "朝阳区三里屯南街4号楼",
            "estimated_budget": 100,
            "notes": "Iconic English bookstore + cafe. Great for browsing and coffee. Open 09:00-22:00. Cozy INFJ-friendly atmosphere."
          },
          {
            "name": "三里屯太古里 (Taikoo Li)",
            "category": "fashion_shopping",
            "location": "三里屯路19号",
            "estimated_budget": 300,
            "notes": "Trendy shopping complex. International and Chinese fashion brands. Modern, young atmosphere."
          }
        ],
        "daily_shopping_budget": 800
      }
    ]
  },
  "total_shopping_budget": 2100,
  "shopping_tips": [
    "Most stores open 10:00-22:00 in China",
    "WeChat Pay and Alipay widely accepted, some stores take international cards",
    "Bargaining not common in modern retail stores or malls",
    "POP MART stores often have blind box exclusives - check release schedules",
    "English bookstores may have limited stock, consider pre-ordering specific titles",
    "Tax-free shopping available at some luxury stores for tourists (passport required)",
    "Luggage capacity: Consider shipping items back if purchasing large items"
  ],
  "location_clusters": {
    "shanghai_day5": "人民广场/南京西路区域 - bookstores and 泡泡玛特 within walking distance",
    "shanghai_day7": "新天地/田子坊区域 - fashion and boutique shopping cluster",
    "beijing_day14": "三里屯太古里 - all shopping locations within same complex or 5min walk"
  },
  "alternatives": {
    "shanghai_bookstores": [
      "久事书店 (Old China Hand Reading Room) - Shaoxing Road, strong English section",
      "衡山·和集 - Hengshan Road, trendy lifestyle bookstore"
    ],
    "beijing_bookstores": [
      "老书虫 (The Bookworm) - listed above, cafe atmosphere",
      "单向空间 (One Way Space) - Chinese focus but some English titles, very artistic"
    ],
    "pop_mart_alternatives": [
      "MINISO (名创优品) - cute affordable items, multiple locations",
      "MUMUSO - Korean-style cute goods stores"
    ]
  }
}
